awshelper/__init__.py
awshelper/cmd_line.py
awshelper/util.py
awshelper-1.6.dist-info/LICENSE.md
awshelper-1.6.dist-info/METADATA
awshelper-1.6.dist-info/WHEEL
awshelper-1.6.dist-info/entry_points.txt
awshelper-1.6.dist-info/top_level.txt
awshelper-1.6.dist-info/RECORD
